spectrify/__init__.py
spectrify/convert.py
spectrify/create.py
spectrify/export.py
spectrify/main.py
spectrify/transform.py
spectrify/utils/__init__.py
spectrify/utils/parquet.py
spectrify/utils/redshift.py
spectrify/utils/s3.py
spectrify/utils/schema.py
spectrify/utils/timestamps.py
spectrify-3.1.0.dist-info/AUTHORS.rst
spectrify-3.1.0.dist-info/LICENSE
spectrify-3.1.0.dist-info/METADATA
spectrify-3.1.0.dist-info/WHEEL
spectrify-3.1.0.dist-info/dependency_links.txt
spectrify-3.1.0.dist-info/entry_points.txt
spectrify-3.1.0.dist-info/top_level.txt
spectrify-3.1.0.dist-info/RECORD
