Metadata-Version: 2.1
Name: spectrify
Version: 3.1.0
Summary: Tools for working with Redshift Spectrum.
Home-page: https://github.com/hellonarrativ/spectrify
Author: The Narrativ Company, Inc.
Author-email: engineering@narrativ.com
License: MIT license
Keywords: spectrify
Platform: UNKNOWN
Classifier: Development Status :: 4 - Beta
Classifier: Intended Audience :: Developers
Classifier: License :: OSI Approved :: MIT License
Classifier: Natural Language :: English
Classifier: Programming Language :: Python :: 2
Classifier: Programming Language :: Python :: 2.7
Classifier: Programming Language :: Python :: 3
Classifier: Programming Language :: Python :: 3.5
Classifier: Programming Language :: Python :: 3.6
Requires-Dist: boto3
Requires-Dist: ciso8601
Requires-Dist: Click
Requires-Dist: future
Requires-Dist: pandas
Requires-Dist: pyarrow (>=0.9.0)
Requires-Dist: python-dateutil (<2.7.0,>=2.1)
Requires-Dist: s3fs
Requires-Dist: sqlalchemy
Requires-Dist: sqlalchemy-redshift (>=0.7.1)
Requires-Dist: unicodecsv
